<?xml version="1.0" encoding="utf-8"?>
<SoundBanksInfo Platform="Mac" BasePlatform="Mac" SchemaVersion="12" SoundbankVersion="135">
	<RootPaths>
		<ProjectRoot>C:\Users\krueg\Documents\GitHub\Cooking_VR\Cooking VR\Cooking VR_WwiseProject\</ProjectRoot>
		<SourceFilesRoot>C:\Users\krueg\Documents\GitHub\Cooking_VR\Cooking VR\Cooking VR_WwiseProject\.cache\Mac\</SourceFilesRoot>
		<SoundBanksRoot>C:\Users\krueg\Documents\GitHub\Cooking_VR\Cooking VR\Cooking VR_WwiseProject\GeneratedSoundBanks\Mac\</SoundBanksRoot>
		<ExternalSourcesInputFile></ExternalSourcesInputFile>
		<ExternalSourcesOutputRoot>C:\Users\krueg\Documents\GitHub\Cooking_VR\Cooking VR\Cooking VR_WwiseProject\GeneratedSoundBanks\Mac</ExternalSourcesOutputRoot>
	</RootPaths>
	<DialogueEvents/>
	<StreamedFiles/>
	<MediaFilesNotInAnyBank/>
	<SoundBanks>
		<SoundBank Id="1355168291" Language="SFX">
			<ObjectPath>Init</ObjectPath>
			<ShortName>Init</ShortName>
			<Path>Init.bnk</Path>
		</SoundBank>
		<SoundBank Id="3989171651" Language="SFX">
			<ObjectPath>\SoundBanks\Default Work Unit\Main_Bank</ObjectPath>
			<ShortName>Main_Bank</ShortName>
			<Path>Main_Bank.bnk</Path>
			<IncludedEvents>
				<Event Id="1710825164" Name="Ambience_Kitchen" ObjectPath="\Events\Default Work Unit\Ambience_Kitchen" DurationType="Infinite">
					<IncludedMemoryFiles>
						<File Id="93227442" Language="SFX">
							<ShortName>sx_ambi_kitchen.wav</ShortName>
							<Path>SFX\sx_ambi_kitchen_D79FB2B7.wem</Path>
						</File>
					</IncludedMemoryFiles>
				</Event>
				<Event Id="1240512178" Name="Bell" ObjectPath="\Events\Default Work Unit\Bell" MaxAttenuation="3.000000" DurationType="OneShot" DurationMin="1.862336" DurationMax="1.862336">
					<IncludedMemoryFiles>
						<File Id="208594037" Language="SFX">
							<ShortName>sx_bell.wav</ShortName>
							<Path>SFX\sx_bell_10C4C929.wem</Path>
						</File>
					</IncludedMemoryFiles>
				</Event>
				<Event Id="3968779560" Name="Burger_Cook_Start" ObjectPath="\Events\Default Work Unit\Burger_Cook_Start" MaxAttenuation="3.000000" DurationType="Infinite">
					<IncludedMemoryFiles>
						<File Id="233327061" Language="SFX">
							<ShortName>sx_burger_cook_start.wav</ShortName>
							<Path>SFX\sx_burger_cook_start_10C4C929.wem</Path>
						</File>
						<File Id="352128800" Language="SFX">
							<ShortName>sx_burger_cook_loop.wav</ShortName>
							<Path>SFX\sx_burger_cook_loop_D79FB2B7.wem</Path>
						</File>
					</IncludedMemoryFiles>
				</Event>
				<Event Id="2163080948" Name="Burger_Cook_Stop" ObjectPath="\Events\Default Work Unit\Burger_Cook_Stop" MaxAttenuation="0.000000" DurationType="OneShot" DurationMin="0.000000" DurationMax="0.000000"/>
				<Event Id="2806512798" Name="Env_Fridge" ObjectPath="\Events\Default Work Unit\Env_Fridge" MaxAttenuation="3.000000" DurationType="Infinite">
					<IncludedMemoryFiles>
						<File Id="781602913" Language="SFX">
							<ShortName>sx_env_fridge.wav</ShortName>
							<Path>SFX\sx_env_fridge_D79FB2B7.wem</Path>
						</File>
					</IncludedMemoryFiles>
				</Event>
				<Event Id="1251402355" Name="Grab_Bottle_Glass" ObjectPath="\Events\Default Work Unit\Grab_Bottle_Glass" DurationType="OneShot" DurationMin="0.240295" DurationMax="0.507029">
					<IncludedMemoryFiles>
						<File Id="141457056" Language="SFX">
							<ShortName>sx_int_glass_bottle_grab_4.wav</ShortName>
							<Path>SFX\sx_int_glass_bottle_grab_4_10C4C929.wem</Path>
						</File>
						<File Id="657838990" Language="SFX">
							<ShortName>sx_int_glass_bottle_grab_5.wav</ShortName>
							<Path>SFX\sx_int_glass_bottle_grab_5_10C4C929.wem</Path>
						</File>
						<File Id="817823556" Language="SFX">
							<ShortName>sx_int_glass_bottle_grab_3.wav</ShortName>
							<Path>SFX\sx_int_glass_bottle_grab_3_10C4C929.wem</Path>
						</File>
						<File Id="838495242" Language="SFX">
							<ShortName>sx_int_glass_bottle_grab_2.wav</ShortName>
							<Path>SFX\sx_int_glass_bottle_grab_2_10C4C929.wem</Path>
						</File>
						<File Id="889619142" Language="SFX">
							<ShortName>sx_int_glass_bottle_grab_1.wav</ShortName>
							<Path>SFX\sx_int_glass_bottle_grab_1_10C4C929.wem</Path>
						</File>
					</IncludedMemoryFiles>
				</Event>
				<Event Id="2416875919" Name="Grab_Bottle_Plastic" ObjectPath="\Events\Default Work Unit\Grab_Bottle_Plastic" DurationType="OneShot" DurationMin="0.329478" DurationMax="0.563673">
					<IncludedMemoryFiles>
						<File Id="205173241" Language="SFX">
							<ShortName>sx_int_plastic_bottle_grab_4.wav</ShortName>
							<Path>SFX\sx_int_plastic_bottle_grab_4_10C4C929.wem</Path>
						</File>
						<File Id="279788534" Language="SFX">
							<ShortName>sx_int_plastic_bottle_grab_2.wav</ShortName>
							<Path>SFX\sx_int_plastic_bottle_grab_2_10C4C929.wem</Path>
						</File>
						<File Id="378245175" Language="SFX">
							<ShortName>sx_int_plastic_bottle_grab_3.wav</ShortName>
							<Path>SFX\sx_int_plastic_bottle_grab_3_10C4C929.wem</Path>
						</File>
						<File Id="1072177874" Language="SFX">
							<ShortName>sx_int_plastic_bottle_grab_1.wav</ShortName>
							<Path>SFX\sx_int_plastic_bottle_grab_1_10C4C929.wem</Path>
						</File>
					</IncludedMemoryFiles>
				</Event>
				<Event Id="1863953098" Name="Grab_Plate" ObjectPath="\Events\Default Work Unit\Grab_Plate" DurationType="OneShot" DurationMin="0.443042" DurationMax="0.689042">
					<IncludedMemoryFiles>
						<File Id="202225013" Language="SFX">
							<ShortName>sx_int_plate_grab_1.wav</ShortName>
							<Path>SFX\sx_int_plate_grab_1_10C4C929.wem</Path>
						</File>
						<File Id="716783425" Language="SFX">
							<ShortName>sx_int_plate_grab_4.wav</ShortName>
							<Path>SFX\sx_int_plate_grab_4_10C4C929.wem</Path>
						</File>
						<File Id="986648341" Language="SFX">
							<ShortName>sx_int_plate_grab_2.wav</ShortName>
							<Path>SFX\sx_int_plate_grab_2_10C4C929.wem</Path>
						</File>
						<File Id="999296791" Language="SFX">
							<ShortName>sx_int_plate_grab_3.wav</ShortName>
							<Path>SFX\sx_int_plate_grab_3_10C4C929.wem</Path>
						</File>
					</IncludedMemoryFiles>
				</Event>
				<Event Id="2236363231" Name="Impact_Extinguisher" ObjectPath="\Events\Default Work Unit\Impact_Extinguisher" MaxAttenuation="3.000000" DurationType="OneShot" DurationMin="0.430992" DurationMax="0.470000">
					<IncludedMemoryFiles>
						<File Id="881847866" Language="SFX">
							<ShortName>sx_impact_extinguisher.wav</ShortName>
							<Path>SFX\sx_impact_extinguisher_10C4C929.wem</Path>
						</File>
					</IncludedMemoryFiles>
				</Event>
				<Event Id="2552890829" Name="Impact_Knife" ObjectPath="\Events\Default Work Unit\Impact_Knife" MaxAttenuation="3.000000" DurationType="OneShot" DurationMin="0.409086" DurationMax="0.522834">
					<IncludedMemoryFiles>
						<File Id="31563926" Language="SFX">
							<ShortName>sx_impact_knife_Layer_1_C.wav</ShortName>
							<Path>SFX\sx_impact_knife_Layer_1_C_10C4C929.wem</Path>
						</File>
						<File Id="84462139" Language="SFX">
							<ShortName>sx_impact_knife_Layer_2_B.wav</ShortName>
							<Path>SFX\sx_impact_knife_Layer_2_B_10C4C929.wem</Path>
						</File>
						<File Id="327731463" Language="SFX">
							<ShortName>sx_impact_knife_Layer_2_C.wav</ShortName>
							<Path>SFX\sx_impact_knife_Layer_2_C_10C4C929.wem</Path>
						</File>
						<File Id="555508597" Language="SFX">
							<ShortName>sx_impact_knife_Layer_1_B.wav</ShortName>
							<Path>SFX\sx_impact_knife_Layer_1_B_10C4C929.wem</Path>
						</File>
						<File Id="848107566" Language="SFX">
							<ShortName>sx_impact_knife_Layer_1_A.wav</ShortName>
							<Path>SFX\sx_impact_knife_Layer_1_A_10C4C929.wem</Path>
						</File>
						<File Id="993571655" Language="SFX">
							<ShortName>sx_impact_knife_Layer_2_A.wav</ShortName>
							<Path>SFX\sx_impact_knife_Layer_2_A_10C4C929.wem</Path>
						</File>
					</IncludedMemoryFiles>
				</Event>
				<Event Id="3360486203" Name="Impact_Meat" ObjectPath="\Events\Default Work Unit\Impact_Meat" MaxAttenuation="3.000000" DurationType="OneShot" DurationMin="0.288396" DurationMax="0.288396">
					<IncludedMemoryFiles>
						<File Id="472009487" Language="SFX">
							<ShortName>sx_meat_impact_1.wav</ShortName>
							<Path>SFX\sx_meat_impact_1_10C4C929.wem</Path>
						</File>
					</IncludedMemoryFiles>
				</Event>
				<Event Id="803254130" Name="Impact_Plate" ObjectPath="\Events\Default Work Unit\Impact_Plate" MaxAttenuation="3.000000" DurationType="OneShot" DurationMin="0.168604" DurationMax="0.254989">
					<IncludedMemoryFiles>
						<File Id="163219809" Language="SFX">
							<ShortName>sx_impact_plate_3.wav</ShortName>
							<Path>SFX\sx_impact_plate_3_10C4C929.wem</Path>
						</File>
						<File Id="447831562" Language="SFX">
							<ShortName>sx_impact_plate_1.wav</ShortName>
							<Path>SFX\sx_impact_plate_1_10C4C929.wem</Path>
						</File>
						<File Id="874152463" Language="SFX">
							<ShortName>sx_impact_plate_2.wav</ShortName>
							<Path>SFX\sx_impact_plate_2_10C4C929.wem</Path>
						</File>
					</IncludedMemoryFiles>
				</Event>
				<Event Id="2540397042" Name="Impact_Silverware" ObjectPath="\Events\Default Work Unit\Impact_Silverware" MaxAttenuation="3.000000" DurationType="OneShot" DurationMin="0.397285" DurationMax="0.511111">
					<IncludedMemoryFiles>
						<File Id="50696179" Language="SFX">
							<ShortName>sx_impact_silverware_3.wav</ShortName>
							<Path>SFX\sx_impact_silverware_3_10C4C929.wem</Path>
						</File>
						<File Id="363414120" Language="SFX">
							<ShortName>sx_impact_silverware_2.wav</ShortName>
							<Path>SFX\sx_impact_silverware_2_10C4C929.wem</Path>
						</File>
						<File Id="444163542" Language="SFX">
							<ShortName>sx_impact_silverware_4.wav</ShortName>
							<Path>SFX\sx_impact_silverware_4_10C4C929.wem</Path>
						</File>
						<File Id="524998403" Language="SFX">
							<ShortName>sx_impact_silverware_1.wav</ShortName>
							<Path>SFX\sx_impact_silverware_1_10C4C929.wem</Path>
						</File>
					</IncludedMemoryFiles>
				</Event>
				<Event Id="2831748783" Name="Knife_Cut_Generic" ObjectPath="\Events\Default Work Unit\Knife_Cut_Generic" MaxAttenuation="2.000000" DurationType="OneShot" DurationMin="0.348046" DurationMax="0.379546">
					<IncludedMemoryFiles>
						<File Id="947404325" Language="SFX">
							<ShortName>sx_knife_cut_generic.wav</ShortName>
							<Path>SFX\sx_knife_cut_generic_10C4C929.wem</Path>
						</File>
					</IncludedMemoryFiles>
				</Event>
				<Event Id="2932040671" Name="Play_Music" ObjectPath="\Events\Default Work Unit\Play_Music" DurationType="Infinite">
					<IncludedMemoryFiles>
						<File Id="108253935" Language="SFX">
							<ShortName>HYB_Lvl2_[LOOP]_05.07.20_v02.wav</ShortName>
							<Path>SFX\HYB_Lvl2_[LOOP]_05.07.20_v02_D79FB2B7.wem</Path>
						</File>
						<File Id="518395074" Language="SFX">
							<ShortName>HYB_Lvl3_[LOOP]_MainTheme_05.07.20_v02.wav</ShortName>
							<Path>SFX\HYB_Lvl3_[LOOP]_MainTheme_05.07.20_v02_D79FB2B7.wem</Path>
						</File>
						<File Id="526915538" Language="SFX">
							<ShortName>HYB_Lvl1_[LOOP]_05.07.20_v01.wav</ShortName>
							<Path>SFX\HYB_Lvl1_[LOOP]_05.07.20_v01_D79FB2B7.wem</Path>
						</File>
					</IncludedMemoryFiles>
					<SwitchContainers>
						<SwitchContainer SwitchValue="{4E7F316C-B27C-4209-8AB0-8395AC865741}">
							<Media>
								<File Id="526915538"/>
							</Media>
						</SwitchContainer>
						<SwitchContainer SwitchValue="{1DDBA1B0-D8AF-4BD9-97C5-33D38871BE6F}">
							<Media>
								<File Id="108253935"/>
							</Media>
						</SwitchContainer>
						<SwitchContainer SwitchValue="{359B949B-9A64-47BC-8BEF-7B5A02E3B81B}">
							<Media>
								<File Id="518395074"/>
							</Media>
						</SwitchContainer>
					</SwitchContainers>
				</Event>
				<Event Id="1603068616" Name="Play_vx_a_1" ObjectPath="\Events\Default Work Unit\VO\Play_vx_a_1" MaxAttenuation="5.000000" DurationType="OneShot" DurationMin="15.639206" DurationMax="15.639206">
					<IncludedMemoryFiles>
						<File Id="217978393" Language="SFX">
							<ShortName>vx_a_1.wav</ShortName>
							<Path>SFX\vx_a_1_10C4C929.wem</Path>
						</File>
					</IncludedMemoryFiles>
				</Event>
				<Event Id="1603068619" Name="Play_vx_a_2" ObjectPath="\Events\Default Work Unit\VO\Play_vx_a_2" MaxAttenuation="5.000000" DurationType="OneShot" DurationMin="10.845193" DurationMax="10.845193">
					<IncludedMemoryFiles>
						<File Id="474374849" Language="SFX">
							<ShortName>vx_a_2_b.wav</ShortName>
							<Path>SFX\vx_a_2_b_10C4C929.wem</Path>
						</File>
					</IncludedMemoryFiles>
				</Event>
				<Event Id="1603068618" Name="Play_vx_a_3" ObjectPath="\Events\Default Work Unit\VO\Play_vx_a_3" MaxAttenuation="5.000000" DurationType="OneShot" DurationMin="10.080476" DurationMax="10.080476">
					<IncludedMemoryFiles>
						<File Id="569838462" Language="SFX">
							<ShortName>vx_a_3_b.wav</ShortName>
							<Path>SFX\vx_a_3_b_10C4C929.wem</Path>
						</File>
					</IncludedMemoryFiles>
				</Event>
				<Event Id="1603068621" Name="Play_vx_a_4" ObjectPath="\Events\Default Work Unit\VO\Play_vx_a_4" MaxAttenuation="5.000000" DurationType="OneShot" DurationMin="2.073968" DurationMax="2.073968">
					<IncludedMemoryFiles>
						<File Id="814098630" Language="SFX">
							<ShortName>vx_a_4_b.wav</ShortName>
							<Path>SFX\vx_a_4_b_10C4C929.wem</Path>
						</File>
					</IncludedMemoryFiles>
				</Event>
				<Event Id="1603068620" Name="Play_vx_a_5" ObjectPath="\Events\Default Work Unit\VO\Play_vx_a_5" MaxAttenuation="5.000000" DurationType="OneShot" DurationMin="10.225873" DurationMax="10.225873">
					<IncludedMemoryFiles>
						<File Id="309232918" Language="SFX">
							<ShortName>vx_a_5.wav</ShortName>
							<Path>SFX\vx_a_5_10C4C929.wem</Path>
						</File>
					</IncludedMemoryFiles>
				</Event>
				<Event Id="1603509903" Name="Play_vx_b_1" ObjectPath="\Events\Default Work Unit\VO\Play_vx_b_1" MaxAttenuation="5.000000" DurationType="OneShot" DurationMin="3.322018" DurationMax="3.322018">
					<IncludedMemoryFiles>
						<File Id="142578265" Language="SFX">
							<ShortName>vx_b_1.wav</ShortName>
							<Path>SFX\vx_b_1_10C4C929.wem</Path>
						</File>
					</IncludedMemoryFiles>
				</Event>
				<Event Id="1603509900" Name="Play_vx_b_2" ObjectPath="\Events\Default Work Unit\VO\Play_vx_b_2" MaxAttenuation="5.000000" DurationType="OneShot" DurationMin="2.894195" DurationMax="2.894195">
					<IncludedMemoryFiles>
						<File Id="335643558" Language="SFX">
							<ShortName>vx_b_2.wav</ShortName>
							<Path>SFX\vx_b_2_10C4C929.wem</Path>
						</File>
					</IncludedMemoryFiles>
				</Event>
				<Event Id="1603509901" Name="Play_vx_b_3" ObjectPath="\Events\Default Work Unit\VO\Play_vx_b_3" MaxAttenuation="5.000000" DurationType="OneShot" DurationMin="4.384059" DurationMax="4.384059">
					<IncludedMemoryFiles>
						<File Id="269172882" Language="SFX">
							<ShortName>vx_b_3.wav</ShortName>
							<Path>SFX\vx_b_3_10C4C929.wem</Path>
						</File>
					</IncludedMemoryFiles>
				</Event>
				<Event Id="1603509898" Name="Play_vx_b_4" ObjectPath="\Events\Default Work Unit\VO\Play_vx_b_4" MaxAttenuation="5.000000" DurationType="OneShot" DurationMin="4.135692" DurationMax="4.135692">
					<IncludedMemoryFiles>
						<File Id="567999839" Language="SFX">
							<ShortName>vx_b_4.wav</ShortName>
							<Path>SFX\vx_b_4_10C4C929.wem</Path>
						</File>
					</IncludedMemoryFiles>
				</Event>
				<Event Id="1603509899" Name="Play_vx_b_5" ObjectPath="\Events\Default Work Unit\VO\Play_vx_b_5" MaxAttenuation="5.000000" DurationType="OneShot" DurationMin="6.591859" DurationMax="6.591859">
					<IncludedMemoryFiles>
						<File Id="171099121" Language="SFX">
							<ShortName>vx_b_5.wav</ShortName>
							<Path>SFX\vx_b_5_10C4C929.wem</Path>
						</File>
					</IncludedMemoryFiles>
				</Event>
				<Event Id="1603509896" Name="Play_vx_b_6" ObjectPath="\Events\Default Work Unit\VO\Play_vx_b_6" MaxAttenuation="5.000000" DurationType="OneShot" DurationMin="2.163288" DurationMax="2.163288">
					<IncludedMemoryFiles>
						<File Id="52499773" Language="SFX">
							<ShortName>vx_b_6.wav</ShortName>
							<Path>SFX\vx_b_6_10C4C929.wem</Path>
						</File>
					</IncludedMemoryFiles>
				</Event>
				<Event Id="1603509897" Name="Play_vx_b_7" ObjectPath="\Events\Default Work Unit\VO\Play_vx_b_7" MaxAttenuation="5.000000" DurationType="OneShot" DurationMin="2.295193" DurationMax="2.295193">
					<IncludedMemoryFiles>
						<File Id="135099540" Language="SFX">
							<ShortName>vx_b_7.wav</ShortName>
							<Path>SFX\vx_b_7_10C4C929.wem</Path>
						</File>
					</IncludedMemoryFiles>
				</Event>
				<Event Id="1603362838" Name="Play_vx_c_1" ObjectPath="\Events\Default Work Unit\VO\Play_vx_c_1" MaxAttenuation="5.000000" DurationType="OneShot" DurationMin="6.882336" DurationMax="6.882336">
					<IncludedMemoryFiles>
						<File Id="12409130" Language="SFX">
							<ShortName>vx_c_1.wav</ShortName>
							<Path>SFX\vx_c_1_10C4C929.wem</Path>
						</File>
					</IncludedMemoryFiles>
				</Event>
				<Event Id="1603362837" Name="Play_vx_c_2" ObjectPath="\Events\Default Work Unit\VO\Play_vx_c_2" MaxAttenuation="5.000000" DurationType="OneShot" DurationMin="5.418730" DurationMax="5.418730">
					<IncludedMemoryFiles>
						<File Id="775067451" Language="SFX">
							<ShortName>vx_c_2.wav</ShortName>
							<Path>SFX\vx_c_2_10C4C929.wem</Path>
						</File>
					</IncludedMemoryFiles>
				</Event>
				<Event Id="1603362836" Name="Play_vx_c_3" ObjectPath="\Events\Default Work Unit\VO\Play_vx_c_3" MaxAttenuation="5.000000" DurationType="OneShot" DurationMin="3.407392" DurationMax="3.407392">
					<IncludedMemoryFiles>
						<File Id="746895508" Language="SFX">
							<ShortName>vx_c_3.wav</ShortName>
							<Path>SFX\vx_c_3_10C4C929.wem</Path>
						</File>
					</IncludedMemoryFiles>
				</Event>
				<Event Id="2676291781" Name="Play_vx_d_1" ObjectPath="\Events\Default Work Unit\VO\Play_vx_d_1" MaxAttenuation="5.000000" DurationType="OneShot" DurationMin="6.148345" DurationMax="6.148345">
					<IncludedMemoryFiles>
						<File Id="109271278" Language="SFX">
							<ShortName>vx_d_1.wav</ShortName>
							<Path>SFX\vx_d_1_10C4C929.wem</Path>
						</File>
					</IncludedMemoryFiles>
				</Event>
				<Event Id="2676291782" Name="Play_vx_d_2" ObjectPath="\Events\Default Work Unit\VO\Play_vx_d_2" MaxAttenuation="5.000000" DurationType="OneShot" DurationMin="5.149841" DurationMax="5.149841">
					<IncludedMemoryFiles>
						<File Id="293595938" Language="SFX">
							<ShortName>vx_d_2.wav</ShortName>
							<Path>SFX\vx_d_2_10C4C929.wem</Path>
						</File>
					</IncludedMemoryFiles>
				</Event>
				<Event Id="2676291783" Name="Play_vx_d_3" ObjectPath="\Events\Default Work Unit\VO\Play_vx_d_3" MaxAttenuation="5.000000" DurationType="OneShot" DurationMin="7.005646" DurationMax="7.005646">
					<IncludedMemoryFiles>
						<File Id="320836404" Language="SFX">
							<ShortName>vx_d_3.wav</ShortName>
							<Path>SFX\vx_d_3_10C4C929.wem</Path>
						</File>
					</IncludedMemoryFiles>
				</Event>
				<Event Id="1602377132" Name="Play_vx_e_1" ObjectPath="\Events\Default Work Unit\VO\Play_vx_e_1" MaxAttenuation="5.000000" DurationType="OneShot" DurationMin="4.347030" DurationMax="4.347030">
					<IncludedMemoryFiles>
						<File Id="726124587" Language="SFX">
							<ShortName>vx_e_1.wav</ShortName>
							<Path>SFX\vx_e_1_10C4C929.wem</Path>
						</File>
					</IncludedMemoryFiles>
				</Event>
				<Event Id="1602377135" Name="Play_vx_e_2" ObjectPath="\Events\Default Work Unit\VO\Play_vx_e_2" MaxAttenuation="5.000000" DurationType="OneShot" DurationMin="5.251610" DurationMax="5.251610">
					<IncludedMemoryFiles>
						<File Id="303422960" Language="SFX">
							<ShortName>vx_e_2.wav</ShortName>
							<Path>SFX\vx_e_2_10C4C929.wem</Path>
						</File>
					</IncludedMemoryFiles>
				</Event>
				<Event Id="1602377134" Name="Play_vx_e_3" ObjectPath="\Events\Default Work Unit\VO\Play_vx_e_3" MaxAttenuation="5.000000" DurationType="OneShot" DurationMin="4.200567" DurationMax="4.200567">
					<IncludedMemoryFiles>
						<File Id="315240720" Language="SFX">
							<ShortName>vx_e_3.wav</ShortName>
							<Path>SFX\vx_e_3_10C4C929.wem</Path>
						</File>
					</IncludedMemoryFiles>
				</Event>
				<Event Id="1602377129" Name="Play_vx_e_4" ObjectPath="\Events\Default Work Unit\VO\Play_vx_e_4" MaxAttenuation="5.000000" DurationType="OneShot" DurationMin="3.283764" DurationMax="3.283764">
					<IncludedMemoryFiles>
						<File Id="806246708" Language="SFX">
							<ShortName>vx_e_4.wav</ShortName>
							<Path>SFX\vx_e_4_10C4C929.wem</Path>
						</File>
					</IncludedMemoryFiles>
				</Event>
				<Event Id="1602921555" Name="Play_vx_f_1" ObjectPath="\Events\Default Work Unit\VO\Play_vx_f_1" MaxAttenuation="5.000000" DurationType="OneShot" DurationMin="4.996871" DurationMax="4.996871">
					<IncludedMemoryFiles>
						<File Id="725862485" Language="SFX">
							<ShortName>vx_f_1.wav</ShortName>
							<Path>SFX\vx_f_1_10C4C929.wem</Path>
						</File>
					</IncludedMemoryFiles>
				</Event>
				<Event Id="1602921552" Name="Play_vx_f_2" ObjectPath="\Events\Default Work Unit\VO\Play_vx_f_2" MaxAttenuation="5.000000" DurationType="OneShot" DurationMin="6.502698" DurationMax="6.502698">
					<IncludedMemoryFiles>
						<File Id="9805013" Language="SFX">
							<ShortName>vx_f_2.wav</ShortName>
							<Path>SFX\vx_f_2_10C4C929.wem</Path>
						</File>
					</IncludedMemoryFiles>
				</Event>
				<Event Id="2676438970" Name="Play_vx_g_1" ObjectPath="\Events\Default Work Unit\VO\Play_vx_g_1" MaxAttenuation="5.000000" DurationType="OneShot" DurationMin="3.697347" DurationMax="3.697347">
					<IncludedMemoryFiles>
						<File Id="522046043" Language="SFX">
							<ShortName>vx_g_1.wav</ShortName>
							<Path>SFX\vx_g_1_10C4C929.wem</Path>
						</File>
					</IncludedMemoryFiles>
				</Event>
				<Event Id="2676438969" Name="Play_vx_g_2" ObjectPath="\Events\Default Work Unit\VO\Play_vx_g_2" MaxAttenuation="5.000000" DurationType="OneShot" DurationMin="2.834263" DurationMax="2.834263">
					<IncludedMemoryFiles>
						<File Id="230967837" Language="SFX">
							<ShortName>vx_g_2.wav</ShortName>
							<Path>SFX\vx_g_2_10C4C929.wem</Path>
						</File>
					</IncludedMemoryFiles>
				</Event>
				<Event Id="2676438968" Name="Play_vx_g_3" ObjectPath="\Events\Default Work Unit\VO\Play_vx_g_3" MaxAttenuation="5.000000" DurationType="OneShot" DurationMin="0.949274" DurationMax="0.949274">
					<IncludedMemoryFiles>
						<File Id="312095112" Language="SFX">
							<ShortName>vx_g_3.wav</ShortName>
							<Path>SFX\vx_g_3_10C4C929.wem</Path>
						</File>
					</IncludedMemoryFiles>
				</Event>
				<Event Id="1604495737" Name="Play_vx_h_1" ObjectPath="\Events\Default Work Unit\VO\Play_vx_h_1" MaxAttenuation="5.000000" DurationType="OneShot" DurationMin="4.296327" DurationMax="4.296327">
					<IncludedMemoryFiles>
						<File Id="634934258" Language="SFX">
							<ShortName>vx_h_1.wav</ShortName>
							<Path>SFX\vx_h_1_10C4C929.wem</Path>
						</File>
					</IncludedMemoryFiles>
				</Event>
				<Event Id="1604495738" Name="Play_vx_h_2" ObjectPath="\Events\Default Work Unit\VO\Play_vx_h_2" MaxAttenuation="5.000000" DurationType="OneShot" DurationMin="2.548435" DurationMax="2.548435">
					<IncludedMemoryFiles>
						<File Id="560762037" Language="SFX">
							<ShortName>vx_h_2.wav</ShortName>
							<Path>SFX\vx_h_2_10C4C929.wem</Path>
						</File>
					</IncludedMemoryFiles>
				</Event>
				<Event Id="1604495739" Name="Play_vx_h_3" ObjectPath="\Events\Default Work Unit\VO\Play_vx_h_3" MaxAttenuation="5.000000" DurationType="OneShot" DurationMin="1.393016" DurationMax="1.661179">
					<IncludedMemoryFiles>
						<File Id="605405818" Language="SFX">
							<ShortName>vx_h_3_a.wav</ShortName>
							<Path>SFX\vx_h_3_a_10C4C929.wem</Path>
						</File>
						<File Id="612696344" Language="SFX">
							<ShortName>vx_h_3_b.wav</ShortName>
							<Path>SFX\vx_h_3_b_10C4C929.wem</Path>
						</File>
					</IncludedMemoryFiles>
				</Event>
				<Event Id="2678116160" Name="Play_vx_i_1" ObjectPath="\Events\Default Work Unit\VO\Play_vx_i_1" MaxAttenuation="5.000000" DurationType="OneShot" DurationMin="2.191814" DurationMax="2.191814">
					<IncludedMemoryFiles>
						<File Id="328395501" Language="SFX">
							<ShortName>vx_i_1.wav</ShortName>
							<Path>SFX\vx_i_1_10C4C929.wem</Path>
						</File>
					</IncludedMemoryFiles>
				</Event>
				<Event Id="2678116163" Name="Play_vx_i_2" ObjectPath="\Events\Default Work Unit\VO\Play_vx_i_2" MaxAttenuation="5.000000" DurationType="OneShot" DurationMin="3.016712" DurationMax="3.016712">
					<IncludedMemoryFiles>
						<File Id="612175400" Language="SFX">
							<ShortName>vx_i_2.wav</ShortName>
							<Path>SFX\vx_i_2_10C4C929.wem</Path>
						</File>
					</IncludedMemoryFiles>
				</Event>
				<Event Id="2678116162" Name="Play_vx_i_3" ObjectPath="\Events\Default Work Unit\VO\Play_vx_i_3" MaxAttenuation="5.000000" DurationType="OneShot" DurationMin="4.376258" DurationMax="4.376258">
					<IncludedMemoryFiles>
						<File Id="900935680" Language="SFX">
							<ShortName>vx_i_3.wav</ShortName>
							<Path>SFX\vx_i_3_10C4C929.wem</Path>
						</File>
					</IncludedMemoryFiles>
				</Event>
				<Event Id="2678116165" Name="Play_vx_i_4" ObjectPath="\Events\Default Work Unit\VO\Play_vx_i_4" MaxAttenuation="5.000000" DurationType="OneShot" DurationMin="4.573197" DurationMax="4.573197">
					<IncludedMemoryFiles>
						<File Id="837826000" Language="SFX">
							<ShortName>vx_i_4.wav</ShortName>
							<Path>SFX\vx_i_4_10C4C929.wem</Path>
						</File>
					</IncludedMemoryFiles>
				</Event>
				<Event Id="2678116164" Name="Play_vx_i_5" ObjectPath="\Events\Default Work Unit\VO\Play_vx_i_5" MaxAttenuation="5.000000" DurationType="OneShot" DurationMin="2.675828" DurationMax="3.848912">
					<IncludedMemoryFiles>
						<File Id="78736221" Language="SFX">
							<ShortName>vx_i_5_b.wav</ShortName>
							<Path>SFX\vx_i_5_b_10C4C929.wem</Path>
						</File>
						<File Id="640329144" Language="SFX">
							<ShortName>vx_i_5_a.wav</ShortName>
							<Path>SFX\vx_i_5_a_10C4C929.wem</Path>
						</File>
					</IncludedMemoryFiles>
				</Event>
				<Event Id="2678116166" Name="Play_vx_i_7" ObjectPath="\Events\Default Work Unit\VO\Play_vx_i_7" MaxAttenuation="5.000000" DurationType="OneShot" DurationMin="0.426213" DurationMax="0.461746">
					<IncludedMemoryFiles>
						<File Id="363543208" Language="SFX">
							<ShortName>vx_i_7_b.wav</ShortName>
							<Path>SFX\vx_i_7_b_10C4C929.wem</Path>
						</File>
						<File Id="375737692" Language="SFX">
							<ShortName>vx_i_7_a.wav</ShortName>
							<Path>SFX\vx_i_7_a_10C4C929.wem</Path>
						</File>
					</IncludedMemoryFiles>
				</Event>
				<Event Id="2678116169" Name="Play_vx_i_8" ObjectPath="\Events\Default Work Unit\VO\Play_vx_i_8" MaxAttenuation="5.000000" DurationType="OneShot" DurationMin="0.989252" DurationMax="1.881814">
					<IncludedMemoryFiles>
						<File Id="573590118" Language="SFX">
							<ShortName>vx_i_8_b.wav</ShortName>
							<Path>SFX\vx_i_8_b_10C4C929.wem</Path>
						</File>
						<File Id="974650106" Language="SFX">
							<ShortName>vx_i_8_a.wav</ShortName>
							<Path>SFX\vx_i_8_a_10C4C929.wem</Path>
						</File>
					</IncludedMemoryFiles>
				</Event>
				<Event Id="2678116168" Name="Play_vx_i_9" ObjectPath="\Events\Default Work Unit\VO\Play_vx_i_9" MaxAttenuation="5.000000" DurationType="OneShot" DurationMin="0.793787" DurationMax="0.869093">
					<IncludedMemoryFiles>
						<File Id="272309235" Language="SFX">
							<ShortName>vx_i_9_a.wav</ShortName>
							<Path>SFX\vx_i_9_a_10C4C929.wem</Path>
						</File>
						<File Id="318910764" Language="SFX">
							<ShortName>vx_i_9_b.wav</ShortName>
							<Path>SFX\vx_i_9_b_10C4C929.wem</Path>
						</File>
					</IncludedMemoryFiles>
				</Event>
				<Event Id="2678557447" Name="Play_vx_j_1" ObjectPath="\Events\Default Work Unit\VO\Play_vx_j_1" MaxAttenuation="5.000000" DurationType="OneShot" DurationMin="0.464422" DurationMax="1.061134">
					<IncludedMemoryFiles>
						<File Id="461070262" Language="SFX">
							<ShortName>vx_j_1_d.wav</ShortName>
							<Path>SFX\vx_j_1_d_10C4C929.wem</Path>
						</File>
						<File Id="503534022" Language="SFX">
							<ShortName>vx_j_1_a.wav</ShortName>
							<Path>SFX\vx_j_1_a_10C4C929.wem</Path>
						</File>
						<File Id="741746257" Language="SFX">
							<ShortName>vx_j_1_c.wav</ShortName>
							<Path>SFX\vx_j_1_c_10C4C929.wem</Path>
						</File>
						<File Id="1062525474" Language="SFX">
							<ShortName>vx_j_1_b.wav</ShortName>
							<Path>SFX\vx_j_1_b_10C4C929.wem</Path>
						</File>
					</IncludedMemoryFiles>
				</Event>
				<Event Id="2678557444" Name="Play_vx_j_2" ObjectPath="\Events\Default Work Unit\VO\Play_vx_j_2" MaxAttenuation="5.000000" DurationType="OneShot" DurationMin="0.480181" DurationMax="0.715737">
					<IncludedMemoryFiles>
						<File Id="65981410" Language="SFX">
							<ShortName>vx_j_2_c.wav</ShortName>
							<Path>SFX\vx_j_2_c_10C4C929.wem</Path>
						</File>
						<File Id="356501855" Language="SFX">
							<ShortName>vx_j_2_b.wav</ShortName>
							<Path>SFX\vx_j_2_b_10C4C929.wem</Path>
						</File>
						<File Id="510687302" Language="SFX">
							<ShortName>vx_j_2_a.wav</ShortName>
							<Path>SFX\vx_j_2_a_10C4C929.wem</Path>
						</File>
						<File Id="595400625" Language="SFX">
							<ShortName>vx_j_2_d.wav</ShortName>
							<Path>SFX\vx_j_2_d_10C4C929.wem</Path>
						</File>
					</IncludedMemoryFiles>
				</Event>
				<Event Id="2678557445" Name="Play_vx_j_3" ObjectPath="\Events\Default Work Unit\VO\Play_vx_j_3" MaxAttenuation="5.000000" DurationType="OneShot" DurationMin="2.627959" DurationMax="3.543696">
					<IncludedMemoryFiles>
						<File Id="343031953" Language="SFX">
							<ShortName>vx_j_3_b.wav</ShortName>
							<Path>SFX\vx_j_3_b_10C4C929.wem</Path>
						</File>
						<File Id="536081949" Language="SFX">
							<ShortName>vx_j_3_a.wav</ShortName>
							<Path>SFX\vx_j_3_a_10C4C929.wem</Path>
						</File>
						<File Id="891193525" Language="SFX">
							<ShortName>vx_j_3_c.wav</ShortName>
							<Path>SFX\vx_j_3_c_10C4C929.wem</Path>
						</File>
					</IncludedMemoryFiles>
				</Event>
				<Event Id="2678557442" Name="Play_vx_j_4" ObjectPath="\Events\Default Work Unit\VO\Play_vx_j_4" MaxAttenuation="5.000000" DurationType="OneShot" DurationMin="8.232835" DurationMax="11.066757">
					<IncludedMemoryFiles>
						<File Id="319996600" Language="SFX">
							<ShortName>vx_j_4_c.wav</ShortName>
							<Path>SFX\vx_j_4_c_10C4C929.wem</Path>
						</File>
						<File Id="950755339" Language="SFX">
							<ShortName>vx_j_4_b.wav</ShortName>
							<Path>SFX\vx_j_4_b_10C4C929.wem</Path>
						</File>
						<File Id="973670549" Language="SFX">
							<ShortName>vx_j_4_a.wav</ShortName>
							<Path>SFX\vx_j_4_a_10C4C929.wem</Path>
						</File>
					</IncludedMemoryFiles>
				</Event>
				<Event Id="2678557443" Name="Play_vx_j_5" ObjectPath="\Events\Default Work Unit\VO\Play_vx_j_5" MaxAttenuation="5.000000" DurationType="OneShot" DurationMin="5.558027" DurationMax="8.463016">
					<IncludedMemoryFiles>
						<File Id="512838790" Language="SFX">
							<ShortName>vx_j_5_a.wav</ShortName>
							<Path>SFX\vx_j_5_a_10C4C929.wem</Path>
						</File>
						<File Id="749957467" Language="SFX">
							<ShortName>vx_j_5_b.wav</ShortName>
							<Path>SFX\vx_j_5_b_10C4C929.wem</Path>
						</File>
						<File Id="970089154" Language="SFX">
							<ShortName>vx_j_5_c.wav</ShortName>
							<Path>SFX\vx_j_5_c_10C4C929.wem</Path>
						</File>
					</IncludedMemoryFiles>
				</Event>
				<Event Id="2678557440" Name="Play_vx_j_6" ObjectPath="\Events\Default Work Unit\VO\Play_vx_j_6" MaxAttenuation="5.000000" DurationType="OneShot" DurationMin="0.461224" DurationMax="1.153719">
					<IncludedMemoryFiles>
						<File Id="203355376" Language="SFX">
							<ShortName>vx_j_6_e.wav</ShortName>
							<Path>SFX\vx_j_6_e_10C4C929.wem</Path>
						</File>
						<File Id="401096079" Language="SFX">
							<ShortName>vx_j_6_d.wav</ShortName>
							<Path>SFX\vx_j_6_d_10C4C929.wem</Path>
						</File>
						<File Id="854541657" Language="SFX">
							<ShortName>vx_j_6_b.wav</ShortName>
							<Path>SFX\vx_j_6_b_10C4C929.wem</Path>
						</File>
						<File Id="975986493" Language="SFX">
							<ShortName>vx_j_6_a.wav</ShortName>
							<Path>SFX\vx_j_6_a_10C4C929.wem</Path>
						</File>
						<File Id="1001016546" Language="SFX">
							<ShortName>vx_j_6_c.wav</ShortName>
							<Path>SFX\vx_j_6_c_10C4C929.wem</Path>
						</File>
					</IncludedMemoryFiles>
				</Event>
				<Event Id="2678557441" Name="Play_vx_j_7" ObjectPath="\Events\Default Work Unit\VO\Play_vx_j_7" MaxAttenuation="5.000000" DurationType="OneShot" DurationMin="0.213492" DurationMax="0.270363">
					<IncludedMemoryFiles>
						<File Id="29292050" Language="SFX">
							<ShortName>vx_j_7_c.wav</ShortName>
							<Path>SFX\vx_j_7_c_10C4C929.wem</Path>
						</File>
						<File Id="714975463" Language="SFX">
							<ShortName>vx_j_7_a.wav</ShortName>
							<Path>SFX\vx_j_7_a_10C4C929.wem</Path>
						</File>
						<File Id="775294745" Language="SFX">
							<ShortName>vx_j_7_b.wav</ShortName>
							<Path>SFX\vx_j_7_b_10C4C929.wem</Path>
						</File>
					</IncludedMemoryFiles>
				</Event>
				<Event Id="2677571741" Name="Play_vx_l_1" ObjectPath="\Events\Default Work Unit\VO\Play_vx_l_1" MaxAttenuation="5.000000" DurationType="OneShot" DurationMin="2.087891" DurationMax="2.087891">
					<IncludedMemoryFiles>
						<File Id="60957674" Language="SFX">
							<ShortName>vx_l_1.wav</ShortName>
							<Path>SFX\vx_l_1_10C4C929.wem</Path>
						</File>
					</IncludedMemoryFiles>
				</Event>
				<Event Id="2677571742" Name="Play_vx_l_2" ObjectPath="\Events\Default Work Unit\VO\Play_vx_l_2" MaxAttenuation="5.000000" DurationType="OneShot" DurationMin="2.053243" DurationMax="2.053243">
					<IncludedMemoryFiles>
						<File Id="569485155" Language="SFX">
							<ShortName>vx_l_2.wav</ShortName>
							<Path>SFX\vx_l_2_10C4C929.wem</Path>
						</File>
					</IncludedMemoryFiles>
				</Event>
				<Event Id="2677571738" Name="Play_vx_l_6" ObjectPath="\Events\Default Work Unit\VO\Play_vx_l_6" MaxAttenuation="5.000000" DurationType="OneShot" DurationMin="2.175601" DurationMax="2.175601">
					<IncludedMemoryFiles>
						<File Id="354167258" Language="SFX">
							<ShortName>vx_l_6.wav</ShortName>
							<Path>SFX\vx_l_6_10C4C929.wem</Path>
						</File>
					</IncludedMemoryFiles>
				</Event>
				<Event Id="2677571732" Name="Play_vx_l_8" ObjectPath="\Events\Default Work Unit\VO\Play_vx_l_8" MaxAttenuation="5.000000" DurationType="OneShot" DurationMin="4.257098" DurationMax="4.257098">
					<IncludedMemoryFiles>
						<File Id="549140607" Language="SFX">
							<ShortName>vx_l_8.wav</ShortName>
							<Path>SFX\vx_l_8_10C4C929.wem</Path>
						</File>
					</IncludedMemoryFiles>
				</Event>
				<Event Id="3025511663" Name="Pour_Bottle_Glass" ObjectPath="\Events\Default Work Unit\Pour_Bottle_Glass" DurationType="OneShot" DurationMin="0.152063" DurationMax="0.278526">
					<IncludedMemoryFiles>
						<File Id="242308609" Language="SFX">
							<ShortName>sx_int_glass_bottle_pour_3.wav</ShortName>
							<Path>SFX\sx_int_glass_bottle_pour_3_10C4C929.wem</Path>
						</File>
						<File Id="406437937" Language="SFX">
							<ShortName>sx_int_glass_bottle_pour_4.wav</ShortName>
							<Path>SFX\sx_int_glass_bottle_pour_4_10C4C929.wem</Path>
						</File>
						<File Id="654708033" Language="SFX">
							<ShortName>sx_int_glass_bottle_pour_2.wav</ShortName>
							<Path>SFX\sx_int_glass_bottle_pour_2_10C4C929.wem</Path>
						</File>
						<File Id="794740313" Language="SFX">
							<ShortName>sx_int_glass_bottle_pour_5.wav</ShortName>
							<Path>SFX\sx_int_glass_bottle_pour_5_10C4C929.wem</Path>
						</File>
						<File Id="1051743148" Language="SFX">
							<ShortName>sx_int_glass_bottle_pour_1.wav</ShortName>
							<Path>SFX\sx_int_glass_bottle_pour_1_10C4C929.wem</Path>
						</File>
					</IncludedMemoryFiles>
				</Event>
				<Event Id="996591275" Name="Stack" ObjectPath="\Events\Default Work Unit\Stack" MaxAttenuation="3.000000" DurationType="OneShot" DurationMin="0.152083" DurationMax="0.152083">
					<IncludedMemoryFiles>
						<File Id="460860198" Language="SFX">
							<ShortName>sx_plr_grab_v2.wav</ShortName>
							<Path>SFX\sx_plr_grab_v2_10C4C929.wem</Path>
						</File>
					</IncludedMemoryFiles>
				</Event>
				<Event Id="1902865914" Name="Stove_Off" ObjectPath="\Events\Default Work Unit\Stove_Off" MaxAttenuation="0.000000" DurationType="OneShot" DurationMin="0.000000" DurationMax="0.000000"/>
				<Event Id="1278791036" Name="Stove_On" ObjectPath="\Events\Default Work Unit\Stove_On" MaxAttenuation="3.000000" DurationType="Infinite">
					<IncludedMemoryFiles>
						<File Id="214031726" Language="SFX">
							<ShortName>sx_stove_loop.wav</ShortName>
							<Path>SFX\sx_stove_loop_D79FB2B7.wem</Path>
						</File>
						<File Id="629777204" Language="SFX">
							<ShortName>sx_stove_ignite.wav</ShortName>
							<Path>SFX\sx_stove_ignite_10C4C929.wem</Path>
						</File>
					</IncludedMemoryFiles>
				</Event>
				<Event Id="2484277510" Name="Use_Condiment" ObjectPath="\Events\Default Work Unit\Use_Condiment" DurationType="OneShot" DurationMin="0.355714" DurationMax="0.476077">
					<IncludedMemoryFiles>
						<File Id="135928796" Language="SFX">
							<ShortName>sx_condiment_squirt_3.wav</ShortName>
							<Path>SFX\sx_condiment_squirt_3_10C4C929.wem</Path>
						</File>
						<File Id="513087279" Language="SFX">
							<ShortName>sx_condiment_squirt_2.wav</ShortName>
							<Path>SFX\sx_condiment_squirt_2_10C4C929.wem</Path>
						</File>
						<File Id="865520128" Language="SFX">
							<ShortName>sx_condiment_squirt_1.wav</ShortName>
							<Path>SFX\sx_condiment_squirt_1_10C4C929.wem</Path>
						</File>
					</IncludedMemoryFiles>
				</Event>
			</IncludedEvents>
			<SwitchGroups>
				<SwitchGroup Id="2470328564" Name="Intensity" ObjectPath="\Switches\Default Work Unit\Intensity">
					<Switches>
						<Switch Id="1290008369" Name="Level_1" ObjectPath="\Switches\Default Work Unit\Intensity\Level_1"/>
						<Switch Id="1290008370" Name="Level_2" ObjectPath="\Switches\Default Work Unit\Intensity\Level_2"/>
						<Switch Id="1290008371" Name="Level_3" ObjectPath="\Switches\Default Work Unit\Intensity\Level_3"/>
					</Switches>
				</SwitchGroup>
			</SwitchGroups>
		</SoundBank>
	</SoundBanks>
</SoundBanksInfo>
